<?xml version="1.0" encoding="UTF-8"?><record_update table="sc_cat_item_category">
    <sc_cat_item_category action="INSERT_OR_UPDATE">
        <sc_cat_item display_value="Requisicao de pedido">b8f91649938b7910eb4db55f7bba10b1</sc_cat_item>
        <sc_category display_value="Pedido de produto">8f295609938b7910eb4db55f7bba1023</sc_category>
        <sys_class_name>sc_cat_item_category</sys_class_name>
        <sys_created_by>admin</sys_created_by>
        <sys_created_on>2023-12-10 01:52:09</sys_created_on>
        <sys_id>dd432a0593cb7910eb4db55f7bba109b</sys_id>
        <sys_mod_count>0</sys_mod_count>
        <sys_name>Pedido de produto.Requisicao de pedido</sys_name>
        <sys_package/>
        <sys_policy/>
        <sys_scope display_value="Gestão de Inventário">1b61753f937ef110eb4db55f7bba10ff</sys_scope>
        <sys_update_name>sc_cat_item_category_dd432a0593cb7910eb4db55f7bba109b</sys_update_name>
        <sys_updated_by>admin</sys_updated_by>
        <sys_updated_on>2023-12-10 01:52:09</sys_updated_on>
    </sc_cat_item_category>
</record_update>
